MANIFEST.in
README.txt
plonetheme.minimalist-configure.zcml
setup.py
docs/AUTHORS.txt
docs/HISTORY.txt
docs/INSTALL.txt
docs/LICENSE.GPL
docs/LICENSE.txt
plonetheme/__init__.py
plonetheme.minimalist.egg-info/PKG-INFO
plonetheme.minimalist.egg-info/SOURCES.txt
plonetheme.minimalist.egg-info/dependency_links.txt
plonetheme.minimalist.egg-info/entry_points.txt
plonetheme.minimalist.egg-info/namespace_packages.txt
plonetheme.minimalist.egg-info/not-zip-safe
plonetheme.minimalist.egg-info/requires.txt
plonetheme.minimalist.egg-info/top_level.txt
plonetheme/minimalist/__init__.py
plonetheme/minimalist/configure.zcml
plonetheme/minimalist/profiles.zcml
plonetheme/minimalist/setuphandlers.py
plonetheme/minimalist/skins.zcml
plonetheme/minimalist/tests.py
plonetheme/minimalist/version.txt
plonetheme/minimalist/browser/__init__.py
plonetheme/minimalist/browser/configure.zcml
plonetheme/minimalist/browser/interfaces.py
plonetheme/minimalist/browser/viewlet.pt
plonetheme/minimalist/browser/viewlets.py
plonetheme/minimalist/browser/images/README.txt
plonetheme/minimalist/browser/stylesheets/main.css
plonetheme/minimalist/browser/templates/search.pt
plonetheme/minimalist/browser/templates/site_actions.pt
plonetheme/minimalist/profiles/default/cssregistry.xml
plonetheme/minimalist/profiles/default/import_steps.xml
plonetheme/minimalist/profiles/default/jsregistry.xml
plonetheme/minimalist/profiles/default/plonetheme.minimalist_various.txt
plonetheme/minimalist/profiles/default/portlets.xml
plonetheme/minimalist/profiles/default/skins.xml
plonetheme/minimalist/profiles/default/viewlets.xml
plonetheme/minimalist/skins/plonetheme_minimalist_custom_images/bg-banner.png
plonetheme/minimalist/skins/plonetheme_minimalist_custom_images/bg-button-header.png
plonetheme/minimalist/skins/plonetheme_minimalist_custom_images/bg-footer.png
plonetheme/minimalist/skins/plonetheme_minimalist_custom_images/bg-header.png
plonetheme/minimalist/skins/plonetheme_minimalist_custom_images/logo.jpg
plonetheme/minimalist/skins/plonetheme_minimalist_custom_images/logominimalist2.jpg
plonetheme/minimalist/skins/plonetheme_minimalist_custom_images/lupa.png
plonetheme/minimalist/skins/plonetheme_minimalist_custom_images/print.png
plonetheme/minimalist/skins/plonetheme_minimalist_custom_images/rss.png
plonetheme/minimalist/skins/plonetheme_minimalist_custom_images/send.png
