Metadata-Version: 1.0
Name: plonetheme.minimalist
Version: 1.0.0a1
Summary: An installable theme for Plone 3.0
Home-page: http://svn.plone.org/svn/collective/plonetheme.minimalist
Author: Marcelo Huens
Author-email: shuens@menttes.com
License: GPL
Keywords: web zope plone theme
Platform: UNKNOWN
Classifier: Framework :: Plone
Classifier: Framework :: Zope2
Classifier: Framework :: Zope3
Classifier: Programming Language :: Python
Classifier: Topic :: Software Development :: Libraries :: Python Modules
